README.md
setup.cfg
setup.py
tirx/__init__.py
tirx.egg-info/PKG-INFO
tirx.egg-info/SOURCES.txt
tirx.egg-info/dependency_links.txt
tirx.egg-info/top_level.txt